leadindicator/__init__.py
leadindicator/analyzer.py
leadindicator/metrics.py
leadindicator/report.py
leadindicator/visualization.py
leadindicator/templates/report.html
leadindicator-0.1.1.dist-info/LICENSE
leadindicator-0.1.1.dist-info/METADATA
leadindicator-0.1.1.dist-info/WHEEL
leadindicator-0.1.1.dist-info/top_level.txt
leadindicator-0.1.1.dist-info/RECORD
