Metadata-Version: 2.2
Name: leadindicator
Version: 0.1.1
Summary: A powerful tool for analyzing leading indicators and setting optimal thresholds
Author: Allen Fruit
Author-email: Harish Batra <hrbatra@utexas.edu>
Project-URL: Homepage, https://github.com/hrbatra/leading-indicators
Project-URL: Bug Tracker, https://github.com/hrbatra/leading-indicators/issues
Classifier: Programming Language :: Python :: 3
Classifier: License :: OSI Approved :: MIT License
Classifier: Operating System :: OS Independent
Classifier: Topic :: Scientific/Engineering :: Information Analysis
Classifier: Development Status :: 4 - Beta
Classifier: Intended Audience :: Science/Research
Classifier: Intended Audience :: Developers
Requires-Python: >=3.8
License-File: LICENSE
Requires-Dist: polars>=1.20.0
Requires-Dist: matplotlib>=3.10.0
Requires-Dist: seaborn>=0.13.2
Requires-Dist: jinja2>=3.1.5
Requires-Dist: pandas>=2.2.0
Dynamic: author
Dynamic: requires-python
